timespeaker/__init__.py
timespeaker/main.py
timespeaker-0.1.6.dist-info/entry_points.txt
timespeaker-0.1.6.dist-info/LICENSE
timespeaker-0.1.6.dist-info/WHEEL
timespeaker-0.1.6.dist-info/METADATA
timespeaker-0.1.6.dist-info/RECORD
