Metadata-Version: 2.1
Name: timespeaker
Version: 0.1.6
Summary: Announce the time every hour similar to Mac OS X. Say the Time using Google TTS or espeak.
Home-page: https://github.com/wallacesilva/timespeaker/
License: MIT
Author: Wallace Silva
Author-email: contact@wallacesilva.com
Requires-Python: >=3.6,<4.0
Classifier: License :: OSI Approved :: MIT License
Classifier: Programming Language :: Python :: 3
Classifier: Programming Language :: Python :: 3.6
Classifier: Programming Language :: Python :: 3.7
Classifier: Programming Language :: Python :: 3.8
Classifier: Programming Language :: Python :: 3.9
Requires-Dist: gtts (>=2.1.1,<3.0.0)
Requires-Dist: pyttsx3 (>=2.90,<3.0)
Project-URL: Bug Tracker, https://github.com/wallacesilva/timespeaker/issues
Project-URL: Documentation, https://github.com/wallacesilva/timespeaker/
Project-URL: Repository, https://github.com/wallacesilva/timespeaker/
